Metadata-Version: 2.2
Name: mat2
Version: 0.13.5
Summary: mat2 is a metadata removal tool, supporting a wide range of commonly used file formats, written in python3: at its core, it's a library, used by an eponymous command-line interface, as well as several file manager extensions.
Home-page: https://0xacab.org/jvoisin/mat2
Author: Julien (jvoisin) Voisin
Author-email: julien.voisin+mat2@dustri.org
License:                    GNU LESSER GENERAL PUBLIC LICENSE
Project-URL: Repository, https://0xacab.org/jvoisin/mat2
Project-URL: Issues, https://0xacab.org/jvoisin/mat2/-/issues
Project-URL: Changelog, https://0xacab.org/jvoisin/mat2/-/blob/master/CHANGELOG.md
Requires-Python: >=3.5.0
License-File: LICENSE
Requires-Dist: mutagen
Requires-Dist: PyGObject
Requires-Dist: pycairo
Dynamic: author
Dynamic: author-email
Dynamic: home-page
Dynamic: requires-python
